clelia_ny2026/__init__.py
clelia_ny2026/fireworks.mp3
clelia_ny2026/new_year.py
clelia_ny2026-0.1.1.dist-info/WHEEL
clelia_ny2026-0.1.1.dist-info/entry_points.txt
clelia_ny2026-0.1.1.dist-info/METADATA
clelia_ny2026-0.1.1.dist-info/RECORD
