Metadata-Version: 2.3
Name: clelia-ny2026
Version: 0.1.1
Summary: Happy new year from Clelia!
Requires-Dist: nava>=0.8
Requires-Dist: rich>=14.2.0
Requires-Python: >=3.10
